[
  {
    "id": "1",
    "name": "Vancouver Convention Centre",
    "capacity": 10000,
    "latitude": "49.2891",
    "longitude": "-123.1162",
    "contact": "604-123-4567",
    "placeType": ["Convention Center"],
    "eventsType": ["Conference", "Exhibition", "Trade Show"],
    "address": "1055 Canada Pl, Vancouver, BC V6C 0C3",
    "histories": [
      {
        "eventName": "TED Conference",
        "eventOrganizer": "TED",
        "date": "2023-04-10",
        "eventType": "Conference",
        "url": "https://www.ted.com/attend/conferences/ted-conference"
      },
      {
        "eventName": "Vancouver International Auto Show",
        "eventOrganizer": "New Car Dealers Association of BC",
        "date": "2022-03-23",
        "eventType": "Exhibition",
        "url": "https://vancouverinternationalautoshow.com"
      }
    ]
  },
  {
    "id": "2",
    "name": "Queen Elizabeth Theatre",
    "capacity": 2800,
    "latitude": "49.2797",
    "longitude": "-123.1122",
    "contact": "604-123-7890",
    "placeType": ["Theatre"],
    "eventsType": ["Concert", "Theater", "Dance Performance"],
    "address": "630 Hamilton St, Vancouver, BC V6B 5N6",
    "histories": [
      {
        "eventName": "Vancouver Opera: La Traviata",
        "eventOrganizer": "Vancouver Opera",
        "date": "2023-09-15",
        "eventType": "Opera",
        "url": "https://www.vancouveropera.ca"
      },
      {
        "eventName": "Broadway Across Canada: Hamilton",
        "eventOrganizer": "Broadway Across Canada",
        "date": "2022-05-02",
        "eventType": "Theater",
        "url": "https://broadwayacrosscanada.ca"
      }
    ]
  },
  {
    "id": "3",
    "name": "Rogers Arena",
    "capacity": 18810,
    "latitude": "49.2775",
    "longitude": "-123.1080",
    "contact": "604-555-0123",
    "placeType": ["Stadium"],
    "eventsType": ["Sports", "Concert", "Exhibition"],
    "address": "800 Griffiths Way, Vancouver, BC V6B 6G1",
    "histories": [
      {
        "eventName": "Vancouver Canucks vs. Toronto Maple Leafs",
        "eventOrganizer": "NHL",
        "date": "2023-11-05",
        "eventType": "Sports",
        "url": "https://www.nhl.com/canucks"
      },
      {
        "eventName": "Elton John Farewell Yellow Brick Road Tour",
        "eventOrganizer": "Elton John",
        "date": "2022-10-21",
        "eventType": "Concert",
        "url": "https://www.eltonjohn.com"
      }
    ]
  },
  {
    "id": "4",
    "name": "Orpheum Theatre",
    "capacity": 2780,
    "latitude": "49.2796",
    "longitude": "-123.1215",
    "contact": "604-555-5678",
    "placeType": ["Theatre"],
    "eventsType": ["Concert", "Theater", "Opera"],
    "address": "601 Smithe St, Vancouver, BC V6B 3L4",
    "histories": [
      {
        "eventName": "Vancouver Symphony Orchestra: Beethoven’s Ninth",
        "eventOrganizer": "Vancouver Symphony Orchestra",
        "date": "2023-12-31",
        "eventType": "Concert",
        "url": "https://www.vancouversymphony.ca"
      },
      {
        "eventName": "Comedy Night with Trevor Noah",
        "eventOrganizer": "Trevor Noah",
        "date": "2022-09-10",
        "eventType": "Comedy Show",
        "url": "https://www.trevornoah.com"
      }
    ]
  },
  {
    "id": "5",
    "name": "Pacific Coliseum",
    "capacity": 16481,
    "latitude": "49.2827",
    "longitude": "-123.0453",
    "contact": "604-555-0987",
    "placeType": ["Arena"],
    "eventsType": ["Sports", "Concert", "Trade Show"],
    "address": "100 N Renfrew St, Vancouver, BC V5K 3N7",
    "histories": [
      {
        "eventName": "PNE Summer Night Concerts",
        "eventOrganizer": "PNE",
        "date": "2023-08-25",
        "eventType": "Concert",
        "url": "https://www.pne.ca/concerts"
      },
      {
        "eventName": "Vancouver Giants vs. Victoria Royals",
        "eventOrganizer": "WHL",
        "date": "2022-11-12",
        "eventType": "Sports",
        "url": "https://vancouvergiants.com"
      }
    ]
  },
  {
    "id": "6",
    "name": "BC Place Stadium",
    "capacity": 54320,
    "latitude": "49.2768",
    "longitude": "-123.1115",
    "contact": "604-555-8765",
    "placeType": ["Stadium"],
    "eventsType": ["Sports", "Concert", "Exhibition"],
    "address": "777 Pacific Blvd, Vancouver, BC V6B 4Y8",
    "histories": [
      {
        "eventName": "Vancouver Whitecaps vs. Seattle Sounders",
        "eventOrganizer": "MLS",
        "date": "2023-07-08",
        "eventType": "Sports",
        "url": "https://www.whitecapsfc.com"
      },
      {
        "eventName": "Ed Sheeran - Mathematics Tour",
        "eventOrganizer": "Ed Sheeran",
        "date": "2022-09-02",
        "eventType": "Concert",
        "url": "https://www.edsheeran.com"
      }
    ]
  },
  {
    "id": "7",
    "name": "Chan Centre for the Performing Arts",
    "capacity": 1185,
    "latitude": "49.2693",
    "longitude": "-123.2532",
    "contact": "604-822-2697",
    "placeType": ["Theatre"],
    "eventsType": ["Concert", "Theater", "Lecture"],
    "address": "6265 Crescent Rd, Vancouver, BC V6T 1Z1",
    "histories": [
      {
        "eventName": "UBC Graduation Ceremony",
        "eventOrganizer": "University of British Columbia",
        "date": "2023-05-24",
        "eventType": "Graduation",
        "url": "https://graduation.ubc.ca"
      },
      {
        "eventName": "David Suzuki: The Climate Crisis",
        "eventOrganizer": "David Suzuki Foundation",
        "date": "2022-04-14",
        "eventType": "Lecture",
        "url": "https://davidsuzuki.org"
      }
    ]
  },
  {
    "id": "8",
    "name": "Science World",
    "capacity": 500,
    "latitude": "49.2734",
    "longitude": "-123.1039",
    "contact": "604-443-7440",
    "placeType": ["Museum", "Exhibition Hall"],
    "eventsType": ["Exhibition", "Educational", "Corporate Event"],
    "address": "1455 Quebec St, Vancouver, BC V6A 3Z7",
    "histories": [
      {
        "eventName": "The Science of Pixar",
        "eventOrganizer": "Science World",
        "date": "2023-06-15",
        "eventType": "Exhibition",
        "url": "https://www.scienceworld.ca"
      },
      {
        "eventName": "BC Tech Summit",
        "eventOrganizer": "BC Tech Association",
        "date": "2022-03-22",
        "eventType": "Conference",
        "url": "https://wearebctech.com"
      }
    ]
  },
  {
    "id": "9",
    "name": "PNE Forum",
    "capacity": 4000,
    "latitude": "49.2822",
    "longitude": "-123.0368",
    "contact": "604-253-2311",
    "placeType": ["Exhibition Hall"],
    "eventsType": ["Trade Show", "Exhibition", "Concert"],
    "address": "2901 E Hastings St, Vancouver, BC V5K 5J1",
    "histories": [
      {
        "eventName": "Vancouver Tattoo Show",
        "eventOrganizer": "Vancouver Tattoo Convention",
        "date": "2023-04-15",
        "eventType": "Exhibition",
        "url": "https://vancouvertattooshow.com"
      },
      {
        "eventName": "Vancouver Comic and Toy Show",
        "eventOrganizer": "Vancouver Comic Con",
        "date": "2022-10-30",
        "eventType": "Exhibition",
        "url": "https://vancouvercomiccon.com"
      }
    ]
  },
  {
    "id": "10",
    "name": "Vancouver Playhouse",
    "capacity": 668,
    "latitude": "49.2821",
    "longitude": "-123.1085",
    "contact": "604-665-3050",
    "placeType": ["Theatre"],
    "eventsType": ["Theater", "Concert", "Lecture"],
    "address": "600 Hamilton St, Vancouver, BC V6B 2P1",
    "histories": [
      {
        "eventName": "Vancouver International Film Festival",
        "eventOrganizer": "VIFF",
        "date": "2023-09-28",
        "eventType": "Film Festival",
        "url": "https://viff.org"
      },
      {
        "eventName": "National Geographic Live: Nature Roars Back",
        "eventOrganizer": "National Geographic",
        "date": "2022-11-17",
        "eventType": "Lecture",
        "url": "https://www.nationalgeographic.com/events"
      }
    ]
  },
  {
    "id": "11",
    "name": "UBC Robson Square",
    "capacity": 300,
    "latitude": "49.2827",
    "longitude": "-123.1213",
    "contact": "604-822-3333",
    "placeType": ["Conference Center"],
    "eventsType": ["Conference", "Seminar", "Workshop"],
    "address": "800 Robson St, Vancouver, BC V6Z 3B7",
    "histories": [
      {
        "eventName": "Techstars Startup Weekend Vancouver",
        "eventOrganizer": "Techstars",
        "date": "2023-03-03",
        "eventType": "Workshop",
        "url": "https://startupweekend.org"
      },
      {
        "eventName": "UBC Dialogues: Vancouver",
        "eventOrganizer": "UBC Alumni Association",
        "date": "2022-02-16",
        "eventType": "Seminar",
        "url": "https://www.alumni.ubc.ca"
      }
    ]
  },
  {
    "id": "12",
    "name": "Granville Island Stage",
    "capacity": 440,
    "latitude": "49.2713",
    "longitude": "-123.1345",
    "contact": "604-687-1644",
    "placeType": ["Theatre"],
    "eventsType": ["Theater", "Concert", "Comedy Show"],
    "address": "1585 Johnston St, Vancouver, BC V6H 3R9",
    "histories": [
      {
        "eventName": "Arts Club Theatre Company: Kinky Boots",
        "eventOrganizer": "Arts Club Theatre",
        "date": "2023-05-12",
        "eventType": "Theater",
        "url": "https://artsclub.com"
      },
      {
        "eventName": "Vancouver Fringe Festival",
        "eventOrganizer": "Vancouver Fringe",
        "date": "2022-09-08",
        "eventType": "Theater",
        "url": "https://www.vancouverfringe.com"
      }
    ]
  },
  {
    "id": "13",
    "name": "The Commodore Ballroom",
    "capacity": 990,
    "latitude": "49.2807",
    "longitude": "-123.1203",
    "contact": "604-739-4550",
    "placeType": ["Concert Hall"],
    "eventsType": ["Concert", "Dance", "Corporate Event"],
    "address": "868 Granville St, Vancouver, BC V6Z 1K3",
    "histories": [
      {
        "eventName": "Tame Impala Concert",
        "eventOrganizer": "Live Nation",
        "date": "2023-07-20",
        "eventType": "Concert",
        "url": "https://www.livenation.com"
      },
      {
        "eventName": "Annual New Year's Eve Gala",
        "eventOrganizer": "Commodore Ballroom",
        "date": "2022-12-31",
        "eventType": "Dance",
        "url": "https://www.commodoreballroom.com"
      }
    ]
  },
  {
    "id": "14",
    "name": "Vancouver Art Gallery",
    "capacity": 200,
    "latitude": "49.2829",
    "longitude": "-123.1207",
    "contact": "604-662-4700",
    "placeType": ["Museum"],
    "eventsType": ["Exhibition", "Art Show", "Corporate Event"],
    "address": "750 Hornby St, Vancouver, BC V6Z 2H7",
    "histories": [
      {
        "eventName": "Yoko Ono: Growing Freedom",
        "eventOrganizer": "Vancouver Art Gallery",
        "date": "2023-10-02",
        "eventType": "Art Show",
        "url": "https://www.vanartgallery.bc.ca"
      },
      {
        "eventName": "Takashi Murakami: The Octopus Eats Its Own Leg",
        "eventOrganizer": "Vancouver Art Gallery",
        "date": "2022-06-06",
        "eventType": "Exhibition",
        "url": "https://www.vanartgallery.bc.ca"
      }
    ]
  },
  {
    "id": "15",
    "name": "Roundhouse Community Arts & Recreation Centre",
    "capacity": 250,
    "latitude": "49.2736",
    "longitude": "-123.1216",
    "contact": "604-713-1800",
    "placeType": ["Community Center"],
    "eventsType": ["Workshop", "Exhibition", "Community Event"],
    "address": "181 Roundhouse Mews, Vancouver, BC V6Z 2W3",
    "histories": [
      {
        "eventName": "Vancouver International Children's Festival",
        "eventOrganizer": "Children's Festival",
        "date": "2023-05-29",
        "eventType": "Community Event",
        "url": "https://www.childrensfestival.ca"
      },
      {
        "eventName": "Make It Vancouver! Craft Fair",
        "eventOrganizer": "Make It Show",
        "date": "2022-11-24",
        "eventType": "Exhibition",
        "url": "https://makeitshow.ca"
      }
    ]
  }
]
